{
  "slug": "random-doubles-random-dubz-MMT3",
  "url": "https://udisc.com/events/random-doubles-random-dubz-MMT3/leaderboard?round=1&view=scores",
  "date": "2023-05-03",
  "title": "Random Doubles - Random Dubz",
  "num_teams": 12,
  "teams": [
    {
      "position": "T1",
      "placement": 1,
      "tied": true,
      "adjustment": 0,
      "total": -10,
      "players": [
        {
          "name": "Stephen",
          "username": "stephenbourget",
          "user_id": "AFbUVJ5ZPd"
        },
        {
          "name": "Spencer Lynds",
          "username": "spencerl5687",
          "user_id": "GUd1btRJAB"
        }
      ]
    },
    {
      "position": "T1",
      "placement": 1,
      "tied": true,
      "adjustment": 0,
      "total": -10,
      "players": [
        {
          "name": "Tyler Fowler",
          "username": "tylersfowler",
          "user_id": "SbuUrPXqGh"
        },
        {
          "name": "Dima",
          "username": "dimasm777",
          "user_id": "Z8C4apNCYE"
        }
      ]
    },
    {
      "position": "3",
      "placement": 3,
      "tied": false,
      "adjustment": 0,
      "total": -9,
      "players": [
        {
          "name": "Dan Lavs",
          "username": "dlavs19",
          "user_id": "zDlGifxx3q"
        },
        {
          "name": "James Willmuth",
          "username": "willmuth",
          "user_id": "tFrf8p1XBS"
        }
      ]
    },
    {
      "position": "T4",
      "placement": 4,
      "tied": true,
      "adjustment": 0,
      "total": -8,
      "players": [
        {
          "name": "Jared",
          "username": "jmdimascio",
          "user_id": "5TgQZKHF0d"
        },
        {
          "name": "John",
          "username": "jbourget",
          "user_id": "cLO8FzEMPh"
        }
      ]
    },
    {
      "position": "T4",
      "placement": 4,
      "tied": true,
      "adjustment": 0,
      "total": -8,
      "players": [
        {
          "name": "Scatman",
          "username": "scatman",
          "user_id": "qPq7NEVvsm"
        },
        {
          "name": "Keaton",
          "username": "kjalbro",
          "user_id": "PAQa433RTK"
        }
      ]
    },
    {
      "position": "T6",
      "placement": 6,
      "tied": true,
      "adjustment": 0,
      "total": -7,
      "players": [
        {
          "name": "Derek",
          "username": "dmmiller612",
          "user_id": "atSiDxcXse"
        },
        {
          "name": "Eric Wilson",
          "username": "ewills",
          "user_id": "MpYtWKrHgDbpB6vxo"
        }
      ]
    },
    {
      "position": "T6",
      "placement": 6,
      "tied": true,
      "adjustment": 0,
      "total": -7,
      "players": [
        {
          "name": "Max",
          "username": "max7272sp",
          "user_id": "NSn8sy9xdx"
        },
        {
          "name": "bert bogeys",
          "username": "bertjohnson",
          "user_id": "Ny9uwyd6Po"
        }
      ]
    },
    {
      "position": "8",
      "placement": 8,
      "tied": false,
      "adjustment": 0,
      "total": -6,
      "players": [
        {
          "name": "Shane",
          "username": "ssgallagher",
          "user_id": "M23k6wunLr"
        },
        {
          "name": "William McKenzie",
          "username": "wmckenzie",
          "user_id": "NEHcXJRfXt"
        }
      ]
    },
    {
      "position": "T9",
      "placement": 9,
      "tied": true,
      "adjustment": 0,
      "total": -5,
      "players": [
        {
          "name": "Jacob Roumanos",
          "username": "cheezus6279",
          "user_id": "xePM3sH6TjCZpCF8e"
        },
        {
          "name": "Billy Dunne",
          "username": "billydunne",
          "user_id": "o4ellyQDzf"
        }
      ]
    },
    {
      "position": "T9",
      "placement": 9,
      "tied": true,
      "adjustment": 0,
      "total": -5,
      "players": [
        {
          "name": "Kevin R",
          "username": "kevinrob",
          "user_id": "mh1JSqBwns"
        },
        {
          "name": "Daphne",
          "username": "daphne",
          "user_id": "kaH8RZeSIJ"
        }
      ]
    },
    {
      "position": "11",
      "placement": 11,
      "tied": false,
      "adjustment": 0,
      "total": -4,
      "players": [
        {
          "name": "David Ludwig",
          "username": "dlud72",
          "user_id": "ehtv6dPjewSbdfZSb"
        },
        {
          "name": "Adam Green",
          "username": "adamhgreen",
          "user_id": "jNjfZ5GSwBY8nhiwd"
        }
      ]
    },
    {
      "position": "12",
      "placement": 12,
      "tied": false,
      "adjustment": 0,
      "total": -2,
      "players": [
        {
          "name": "Michael Drolet",
          "username": "bigmikedg",
          "user_id": "4t2o3JbRMd"
        },
        {
          "name": "Matt",
          "username": "smit1matt",
          "user_id": "kGAz4xScHT"
        }
      ]
    }
  ]
}